django_restapi_engine/__init__.py
django_restapi_engine/base.py
django_restapi_engine/compiler.py
django_restapi_engine/rest_api_handler.py
django_restapi_engine-0.2.0.dist-info/METADATA
django_restapi_engine-0.2.0.dist-info/WHEEL
django_restapi_engine-0.2.0.dist-info/licenses/LICENSE
django_restapi_engine-0.2.0.dist-info/RECORD
