Metadata-Version: 2.3
Name: django-restapi-engine
Version: 0.2.0
Summary: Use any RestAPI as basic Django Database Engine
Project-URL: Documentation, https://github.com/laroo/django-restapi-engine
Project-URL: Homepage, https://github.com/laroo/django-restapi-engine
Project-URL: Source, https://github.com/laroo/django-restapi-engine
Project-URL: Tracker, https://github.com/laroo/django-restapi-engine/issues
Author: Jan-Age Laroo
License: MIT
Classifier: Framework :: Django
Classifier: Framework :: Django :: 3.2
Classifier: Framework :: Django :: 4.0
Classifier: Framework :: Django :: 4.1
Classifier: License :: OSI Approved :: MIT License
Classifier: Programming Language :: Python :: 3
Classifier: Programming Language :: Python :: 3.7
Classifier: Programming Language :: Python :: 3.8
Classifier: Programming Language :: Python :: 3.9
Classifier: Programming Language :: Python :: 3.10
Classifier: Programming Language :: Python :: 3.11
Requires-Python: >=3.9
Requires-Dist: django>=3.2
